myst_nb/__init__.py
myst_nb/_compat.py
myst_nb/cli.py
myst_nb/docutils_.py
myst_nb/sphinx_.py
myst_nb/sphinx_ext.py
myst_nb/core/__init__.py
myst_nb/core/config.py
myst_nb/core/lexers.py
myst_nb/core/loggers.py
myst_nb/core/nb_to_tokens.py
myst_nb/core/read.py
myst_nb/core/render.py
myst_nb/core/utils.py
myst_nb/core/variables.py
myst_nb/core/execute/__init__.py
myst_nb/core/execute/base.py
myst_nb/core/execute/cache.py
myst_nb/core/execute/direct.py
myst_nb/core/execute/inline.py
myst_nb/ext/__init__.py
myst_nb/ext/download.py
myst_nb/ext/execution_tables.py
myst_nb/ext/utils.py
myst_nb/ext/eval/__init__.py
myst_nb/ext/glue/__init__.py
myst_nb/ext/glue/crossref.py
myst_nb/ext/glue/directives.py
myst_nb/ext/glue/domain.py
myst_nb/ext/glue/roles.py
myst_nb/ext/glue/utils.py
myst_nb/static/__init__.py
myst_nb/static/mystnb.css
myst_nb-0.17.0.dist-info/entry_points.txt
myst_nb-0.17.0.dist-info/LICENSE
myst_nb-0.17.0.dist-info/WHEEL
myst_nb-0.17.0.dist-info/METADATA
myst_nb-0.17.0.dist-info/RECORD
