Metadata-Version: 2.1
Name: myst-nb
Version: 0.17.0
Summary: A Jupyter Notebook Sphinx reader built on top of the MyST markdown parser.
Keywords: markdown,lexer,parser,jupyter,docutils,sphinx
Author-email: ExecutableBookProject <chrisj_sewell@hotmail.com>
Requires-Python: >=3.7
Classifier: Development Status :: 4 - Beta
Classifier: Framework :: Sphinx :: Extension
Classifier: Intended Audience :: Developers
Classifier: License :: OSI Approved :: MIT License
Classifier: Programming Language :: Python :: 3
Classifier: Programming Language :: Python :: 3 :: Only
Classifier: Programming Language :: Python :: 3.7
Classifier: Programming Language :: Python :: 3.8
Classifier: Programming Language :: Python :: 3.9
Classifier: Programming Language :: Python :: 3.10
Classifier: Programming Language :: Python :: Implementation :: CPython
Classifier: Programming Language :: Python :: Implementation :: PyPy
Classifier: Topic :: Software Development :: Libraries :: Python Modules
Classifier: Topic :: Text Processing :: Markup
Requires-Dist: importlib_metadata
Requires-Dist: ipython
Requires-Dist: jupyter-cache~=0.5.0
Requires-Dist: nbclient
Requires-Dist: myst-parser~=0.18.0
Requires-Dist: nbformat~=5.0
Requires-Dist: pyyaml
Requires-Dist: sphinx>=4,<6
Requires-Dist: typing-extensions
Requires-Dist: ipykernel
Requires-Dist: pre-commit ; extra == "code_style"
Requires-Dist: alabaster ; extra == "rtd"
Requires-Dist: altair ; extra == "rtd"
Requires-Dist: bokeh ; extra == "rtd"
Requires-Dist: coconut~=1.4.3 ; extra == "rtd"
Requires-Dist: ipykernel~=5.5 ; extra == "rtd"
Requires-Dist: ipywidgets ; extra == "rtd"
Requires-Dist: jupytext~=1.11.2 ; extra == "rtd"
Requires-Dist: matplotlib ; extra == "rtd"
Requires-Dist: numpy ; extra == "rtd"
Requires-Dist: pandas ; extra == "rtd"
Requires-Dist: plotly ; extra == "rtd"
Requires-Dist: sphinx-book-theme~=0.3.0 ; extra == "rtd"
Requires-Dist: sphinx-copybutton ; extra == "rtd"
Requires-Dist: sphinx-design~=0.1.0 ; extra == "rtd"
Requires-Dist: sphinxcontrib-bibtex ; extra == "rtd"
Requires-Dist: sympy ; extra == "rtd"
Requires-Dist: coverage~=6.4 ; extra == "testing"
Requires-Dist: beautifulsoup4 ; extra == "testing"
Requires-Dist: ipykernel~=5.5 ; extra == "testing"
Requires-Dist: ipython!=8.1.0,<8.5 ; extra == "testing"
Requires-Dist: ipywidgets>=8 ; extra == "testing"
Requires-Dist: jupytext~=1.11.2 ; extra == "testing"
Requires-Dist: matplotlib>=3.5.3,<3.6 ; extra == "testing"
Requires-Dist: nbdime ; extra == "testing"
Requires-Dist: numpy ; extra == "testing"
Requires-Dist: pandas ; extra == "testing"
Requires-Dist: pytest~=7.1 ; extra == "testing"
Requires-Dist: pytest-cov~=3.0 ; extra == "testing"
Requires-Dist: pytest-regressions ; extra == "testing"
Requires-Dist: pytest-param-files~=0.3.3 ; extra == "testing"
Requires-Dist: sympy>=1.10.1 ; extra == "testing"
Project-URL: Documentation, https://myst-nb.readthedocs.io
Project-URL: Homepage, https://github.com/executablebooks/myst-nb
Provides-Extra: code_style
Provides-Extra: rtd
Provides-Extra: testing
